OnImage-0.1.1.data/scripts/benchmark_multi_img_find_multiprocessing.py
on_image/HashingArray.py
on_image/OnImage.py
on_image/__init__.py
on_image/tests/__init__.py
on_image/tests/test_img_search.py
OnImage-0.1.1.dist-info/LICENSE
OnImage-0.1.1.dist-info/METADATA
OnImage-0.1.1.dist-info/WHEEL
OnImage-0.1.1.dist-info/top_level.txt
OnImage-0.1.1.dist-info/RECORD
