Metadata-Version: 2.1
Name: OnImage
Version: 0.1.1
Summary: Simple decorator and class based events, triggered by images detected on-screen.
Home-page: https://github.com/jamd315/OnImage
Author: jamd315
Author-email: lizardswimmer@gmail.com
License: LICENSE.txt
Platform: UNKNOWN
Requires-Dist: Pillow
Requires-Dist: xxhash
Requires-Dist: numpy
Requires-Dist: pyautogui
Requires-Dist: opencv-python
